nmigen_tool/__init__.py
nmigen_tool/cli.py
nmigen_tool-0.0.1.dist-info/LICENSE.txt
nmigen_tool-0.0.1.dist-info/METADATA
nmigen_tool-0.0.1.dist-info/WHEEL
nmigen_tool-0.0.1.dist-info/entry_points.txt
nmigen_tool-0.0.1.dist-info/top_level.txt
nmigen_tool-0.0.1.dist-info/RECORD
