Metadata-Version: 2.1
Name: nmigen-tool
Version: 0.0.1
Summary: nmigen command line tool for generating verilog, rtlil, cxxrtl and showing design diagrams
Home-page: https://github.com/hansfbaier/nmigen-tool/
Author: Hans Baier
Author-email: hansfbaier@gmail.com
License: UNKNOWN
Project-URL: Bug Tracker, https://github.com/hansfbaier/nmigen-tool/issues
Platform: linux
Classifier: Programming Language :: Python :: 3
Classifier: License :: OSI Approved :: BSD License
Classifier: Operating System :: POSIX
Classifier: Intended Audience :: Developers
Classifier: Topic :: Scientific/Engineering :: Electronic Design Automation (EDA)
Requires-Dist: Click
